odoo/addons/stock_picking_report_delivery_custom_name/README.rst
odoo/addons/stock_picking_report_delivery_custom_name/__init__.py
odoo/addons/stock_picking_report_delivery_custom_name/__manifest__.py
odoo/addons/stock_picking_report_delivery_custom_name/i18n/it.po
odoo/addons/stock_picking_report_delivery_custom_name/i18n/stock_picking_report_delivery_custom_name.pot
odoo/addons/stock_picking_report_delivery_custom_name/readme/CONFIGURE.md
odoo/addons/stock_picking_report_delivery_custom_name/readme/CONTEXT.md
odoo/addons/stock_picking_report_delivery_custom_name/readme/DESCRIPTION.md
odoo/addons/stock_picking_report_delivery_custom_name/readme/ROADMAP.md
odoo/addons/stock_picking_report_delivery_custom_name/readme/USAGE.md
odoo/addons/stock_picking_report_delivery_custom_name/static/description/icon.png
odoo/addons/stock_picking_report_delivery_custom_name/static/description/index.html
odoo/addons/stock_picking_report_delivery_custom_name/tests/__init__.py
odoo/addons/stock_picking_report_delivery_custom_name/tests/test_delivery_slip_custom_name.py
odoo/addons/stock_picking_report_delivery_custom_name/views/report_deliveryslip.xml
odoo_addon_stock_picking_report_delivery_custom_name-16.0.1.0.1.1.dist-info/METADATA
odoo_addon_stock_picking_report_delivery_custom_name-16.0.1.0.1.1.dist-info/WHEEL
odoo_addon_stock_picking_report_delivery_custom_name-16.0.1.0.1.1.dist-info/top_level.txt
odoo_addon_stock_picking_report_delivery_custom_name-16.0.1.0.1.1.dist-info/RECORD
